executor/http/__init__.py
executor/http/server/__init__.py
executor/http/server/app.py
executor/http/server/config.py
executor/http/server/task.py
executor/http/server/routers/__init__.py
executor/http/server/routers/file.py
executor/http/server/routers/job.py
executor/http/server/routers/monitor.py
executor/http/server/routers/proxy.py
executor/http/server/routers/task.py
executor/http/server/routers/user.py
executor/http/server/user_db/__init__.py
executor/http/server/user_db/crud.py
executor/http/server/user_db/database.py
executor/http/server/user_db/models.py
executor/http/server/user_db/schemas.py
executor/http/server/user_db/utils.py
executor/http/server/utils/__init__.py
executor/http/server/utils/auth.py
executor/http/server/utils/log.py
executor/http/server/utils/misc.py
executor/http/server/utils/oauth2cookie.py
executor_http-0.1.2.dist-info/LICENSE
executor_http-0.1.2.dist-info/METADATA
executor_http-0.1.2.dist-info/WHEEL
executor_http-0.1.2.dist-info/top_level.txt
executor_http-0.1.2.dist-info/RECORD
