Metadata-Version: 2.1
Name: executor-http
Version: 0.1.2
Summary: HTTP Server and Client for executor.
Home-page: https://github.com/Nanguage/executor-http
Author: Weize Xu
Author-email: vet.xwz@gmail.com
License: MIT
Keywords: Job Management,Web,HTTP
Classifier: Development Status :: 3 - Alpha
Classifier: Operating System :: OS Independent
Classifier: Programming Language :: Python
Classifier: Programming Language :: Python :: 3
Classifier: Programming Language :: Python :: 3.8
Classifier: Programming Language :: Python :: 3.9
Classifier: Programming Language :: Python :: 3.10
Classifier: License :: OSI Approved :: MIT License
Classifier: Intended Audience :: Science/Research
Classifier: Intended Audience :: Developers
Requires-Python: >=3.7, <4
License-File: LICENSE
Requires-Dist: executor-engine>=0.1.6
Requires-Dist: funcdesc>=0.1.2
Requires-Dist: cmd2func>=0.1.6
Requires-Dist: fire
Requires-Dist: fastapi
Requires-Dist: uvicorn
Requires-Dist: python-multipart
Requires-Dist: sqlalchemy
Requires-Dist: aiosqlite
Requires-Dist: passlib[bcrypt]
Requires-Dist: python-jose[cryptography]
Requires-Dist: httpx
Provides-Extra: dask
Requires-Dist: dask; extra == "dask"
Requires-Dist: distributed; extra == "dask"
Requires-Dist: nest-asyncio; extra == "dask"
Provides-Extra: dev
Requires-Dist: pip; extra == "dev"
Requires-Dist: setuptools; extra == "dev"
Requires-Dist: wheel; extra == "dev"
Requires-Dist: twine; extra == "dev"
Requires-Dist: ipdb; extra == "dev"
Requires-Dist: pytest; extra == "dev"
Requires-Dist: pytest-cov; extra == "dev"
Requires-Dist: flake8; extra == "dev"
Requires-Dist: pytest-order; extra == "dev"
Requires-Dist: mypy; extra == "dev"
Requires-Dist: httpx; extra == "dev"
Requires-Dist: pytest-asyncio; extra == "dev"
